basal_and_bark/__init__.py
basal_and_bark/basal_and_bark.py
basal_and_bark/basal_and_bark_folium.py
basal_and_bark-0.0.8.dist-info/LICENSE
basal_and_bark-0.0.8.dist-info/METADATA
basal_and_bark-0.0.8.dist-info/WHEEL
basal_and_bark-0.0.8.dist-info/dependency_links.txt
basal_and_bark-0.0.8.dist-info/top_level.txt
basal_and_bark-0.0.8.dist-info/RECORD
