Metadata-Version: 2.1
Name: basal-and-bark
Version: 0.0.8
Summary: Welcome to Basal and Bark, a spatial python package for working with forest data.
Home-page: https://github.com/ZachDorm/basal_and_bark
Author: Zach Dorminey
Author-email: zach.dorminey@gmail.com
License: MIT license
Keywords: basal_and_bark
Classifier: Development Status :: 2 - Pre-Alpha
Classifier: Intended Audience :: Developers
Classifier: License :: OSI Approved :: MIT License
Classifier: Natural Language :: English
Classifier: Programming Language :: Python :: 3
Classifier: Programming Language :: Python :: 3.7
Classifier: Programming Language :: Python :: 3.8
Classifier: Programming Language :: Python :: 3.9
Classifier: Programming Language :: Python :: 3.10
Requires-Python: >=3.7
License-File: LICENSE
Requires-Dist: folium
Requires-Dist: ipyleaflet
Requires-Dist: geopandas
Requires-Dist: earthengine-api
Requires-Dist: geemap
